socketIO_client_nexus/__init__.py
socketIO_client_nexus/exceptions.py
socketIO_client_nexus/heartbeats.py
socketIO_client_nexus/logs.py
socketIO_client_nexus/namespaces.py
socketIO_client_nexus/parsers.py
socketIO_client_nexus/symmetries.py
socketIO_client_nexus/transports.py
socketIO_client_nexus/tests/__init__.py
socketIO_client_nexus-0.7.6.dist-info/DESCRIPTION.rst
socketIO_client_nexus-0.7.6.dist-info/METADATA
socketIO_client_nexus-0.7.6.dist-info/RECORD
socketIO_client_nexus-0.7.6.dist-info/WHEEL
socketIO_client_nexus-0.7.6.dist-info/metadata.json
socketIO_client_nexus-0.7.6.dist-info/top_level.txt
