Metadata-Version: 1.1
Name: socketIO-client-nexus
Version: 0.7.6
Summary: A socket.io client library
Home-page: https://github.com/nexus-devs/socketIO-client
Author: Roy Hyunjin Han
Author-email: rhh@crosscompute.com
License: MIT
Keywords: socket.io node.js
Platform: UNKNOWN
Classifier: Intended Audience :: Developers
Classifier: Programming Language :: Python
Classifier: License :: OSI Approved :: MIT License
Classifier: Development Status :: 5 - Production/Stable
